aircot/VERSION
aircot/__init__.py
aircot/constants.py
aircot/functions.py
aircot/data/cotdb.json
aircot/data/cotdb.txt
aircot/data/cotdb_indexed.json
aircot/data/countries.json
aircot-4.0.1.dist-info/licenses/LICENSE
aircot-4.0.1.dist-info/METADATA
aircot-4.0.1.dist-info/WHEEL
aircot-4.0.1.dist-info/top_level.txt
aircot-4.0.1.dist-info/RECORD
