Metadata-Version: 2.4
Name: aircot
Version: 4.0.1
Summary: Software for classifying aircraft within TAK.
Home-page: https://github.com/snstac/aircot
Maintainer: Greg Albrecht
Maintainer-email: oss@undef.net
License: Apache-2.0
Project-URL: CI: GitHub Actions, https://github.com/snstac/aircot/actions
Project-URL: GitHub: issues, https://github.com/snstac/aircot/issues
Project-URL: GitHub: repo, https://github.com/snstac/aircot
Keywords: Cursor on Target,ATAK,WinTAK,TAK Server,ADS-B,Aircraft
Classifier: License :: OSI Approved :: Apache Software License
Classifier: Intended Audience :: Developers
Classifier: Programming Language :: Python
Classifier: Programming Language :: Python :: 3
Classifier: Programming Language :: Python :: 3 :: Only
Classifier: Development Status :: 5 - Production/Stable
Classifier: Operating System :: POSIX
Classifier: Operating System :: MacOS :: MacOS X
Classifier: Operating System :: Microsoft :: Windows
Classifier: Operating System :: OS Independent
Requires-Python: >=3.7
License-File: LICENSE
Provides-Extra: test
Requires-Dist: pytest>=6.0; extra == "test"
Requires-Dist: pytest-cov; extra == "test"
Requires-Dist: pylint; extra == "test"
Requires-Dist: flake8; extra == "test"
Requires-Dist: black; extra == "test"
Dynamic: license-file
